setup.py
distributions_gauss_binomial/Binomialdistribution.py
distributions_gauss_binomial/Gaussiandistribution.py
distributions_gauss_binomial/Generaldistribution.py
distributions_gauss_binomial/__init__.py
distributions_gauss_binomial.egg-info/PKG-INFO
distributions_gauss_binomial.egg-info/SOURCES.txt
distributions_gauss_binomial.egg-info/dependency_links.txt
distributions_gauss_binomial.egg-info/not-zip-safe
distributions_gauss_binomial.egg-info/top_level.txt