Metadata-Version: 1.0
Name: distributions-gauss-binomial
Version: 0.1
Summary: Gaussian and Binomial  distributions
Home-page: UNKNOWN
Author: Bhart Gupta
Author-email: bhartgupta4747@gmail.com
License: UNKNOWN
Platform: UNKNOWN
